footing/__init__.py
footing/check.py
footing/clean.py
footing/cli.py
footing/constants.py
footing/exceptions.py
footing/forge.py
footing/ls.py
footing/setup.py
footing/update.py
footing/utils.py
footing/version.py
footing-1.0.1.dist-info/LICENSE
footing-1.0.1.dist-info/METADATA
footing-1.0.1.dist-info/WHEEL
footing-1.0.1.dist-info/entry_points.txt
footing-1.0.1.dist-info/RECORD
